_pyift.cpython-37m-darwin.so
pyift/__init__.py
pyift/_version.py
pyift/shortestpath.py
pyift-0.0.1.dev3.dist-info/LICENSE
pyift-0.0.1.dev3.dist-info/METADATA
pyift-0.0.1.dev3.dist-info/WHEEL
pyift-0.0.1.dev3.dist-info/top_level.txt
pyift-0.0.1.dev3.dist-info/RECORD
