Metadata-Version: 2.1
Name: pyift
Version: 0.0.1.dev3
Summary: Python Image Foresting Transform Library
Home-page: https://github.com/pyift/pyift
Author: Jordao Bragantini
Author-email: jordao.bragantini+pyift@gmail.com
License: MIT
Platform: UNKNOWN
Classifier: Development Status :: 3 - Alpha
Classifier: Intended Audience :: Developers
Classifier: Intended Audience :: Education
Classifier: Intended Audience :: Science/Research
Classifier: License :: OSI Approved :: MIT License
Classifier: Programming Language :: C
Classifier: Programming Language :: Python :: 3
Classifier: Topic :: Scientific/Engineering
Classifier: Topic :: Software Development :: Libraries :: Python Modules
Requires-Dist: numpy
Requires-Dist: scipy
